MANIFEST.in
setup.py
bin/maxillo
bin/maxillo-install
maxillo/__init__.py
maxillo/applications.py
maxillo/branches.py
maxillo/configuration.py
maxillo/definitions.py
maxillo/deployments.py
maxillo/docker.py
maxillo/filters.py
maxillo/git.py
maxillo/keys.py
maxillo/listener.py
maxillo/main.py
maxillo/networking.py
maxillo/setup.py
maxillo/slave.py
maxillo/templates.py
maxillo/volumes.py
maxillo.egg-info/PKG-INFO
maxillo.egg-info/SOURCES.txt
maxillo.egg-info/dependency_links.txt
maxillo.egg-info/requires.txt
maxillo.egg-info/top_level.txt